denkproto/ImageAnalysis_ProtobufMessages_pb2.py
denkproto/ImageAnalysis_ProtobufMessages_pb2.pyi
denkproto/ImageAnalysis_ProtobufMessages_pb2_grpc.py
denkproto/__about__.py
denkproto/__init__.py
denkproto/annotation_comparer_request_pb2.py
denkproto/annotation_comparer_request_pb2.pyi
denkproto/annotation_comparer_request_pb2_grpc.py
denkproto/annotation_comparer_result_pb2.py
denkproto/annotation_comparer_result_pb2.pyi
denkproto/annotation_comparer_result_pb2_grpc.py
denkproto/denkcache_pb2.py
denkproto/denkcache_pb2.pyi
denkproto/denkcache_pb2_grpc.py
denkproto/geometry_pb2.py
denkproto/geometry_pb2.pyi
denkproto/geometry_pb2_grpc.py
denkproto/inference_graph_pb2.py
denkproto/inference_graph_pb2.pyi
denkproto/inference_graph_pb2_grpc.py
denkproto/markup_pb2.py
denkproto/markup_pb2.pyi
denkproto/markup_pb2_grpc.py
denkproto/materialized_markup_pb2.py
denkproto/materialized_markup_pb2.pyi
denkproto/materialized_markup_pb2_grpc.py
denkproto/modelfile_v1_pb2.py
denkproto/modelfile_v1_pb2.pyi
denkproto/modelfile_v1_pb2_grpc.py
denkproto/modelfile_v2_pb2.py
denkproto/modelfile_v2_pb2.pyi
denkproto/modelfile_v2_pb2_grpc.py
denkproto/prediction_pb2.py
denkproto/prediction_pb2.pyi
denkproto/prediction_pb2_grpc.py
denkproto/prediction_request_pb2.py
denkproto/prediction_request_pb2.pyi
denkproto/prediction_request_pb2_grpc.py
denkproto/py.typed
denkproto/request_pb2.py
denkproto/request_pb2.pyi
denkproto/request_pb2_grpc.py
denkproto/results_pb2.py
denkproto/results_pb2.pyi
denkproto/results_pb2_grpc.py
denkproto/validate_pb2.py
denkproto/validate_pb2.pyi
denkproto/validate_pb2_grpc.py
denkproto/json/__init__.py
denkproto/json/classification_markup_schema.py
denkproto/json/classification_markup_schema_.py
denkproto/json/geometry_schema.py
denkproto/json/inference_graph_recipe_schema.py
denkproto/json/instance_segmentation_markup_schema.py
denkproto/json/object_detection_markup_schema.py
denkproto/json/ocr_markup_schema.py
denkproto/json/segmentation_markup_schema.py
denkproto-1.6.1.dist-info/METADATA
denkproto-1.6.1.dist-info/WHEEL
denkproto-1.6.1.dist-info/RECORD
