Metadata-Version: 2.4
Name: denkproto
Version: 1.6.1
Requires-Python: >=3.10
Requires-Dist: protobuf>=3.20.3
